{"commitInfo":{"timestamp":1765642887440,"operation":"STREAMING UPDATE","operationParameters":{"outputMode":"Append","queryId":"c21f1fb7-6ebd-4aca-9520-4d1507940f2c","epochId":"654"},"readVersion":653,"isolationLevel":"Serializable","isBlindAppend":true,"operationMetrics":{"numRemovedFiles":"0","numOutputRows":"15","numOutputBytes":"1503","numAddedFiles":"1"},"engineInfo":"Apache-Spark/3.5.7 Delta-Lake/3.1.0","txnId":"004f9a80-3e2e-4448-8ac0-a889629c289d"}}
{"txn":{"appId":"c21f1fb7-6ebd-4aca-9520-4d1507940f2c","version":654,"lastUpdated":1765642887440}}
{"add":{"path":"part-00000-ca9b6f58-11ac-4823-9838-030194b04080-c000.snappy.parquet","partitionValues":{},"size":1503,"modificationTime":1765642887434,"dataChange":true,"stats":"{\"numRecords\":15,\"minValues\":{\"from_user\":\"user13\",\"to_user\":\"user1\",\"action\":\"COMMENT\",\"event_time\":\"2025-12-13T17:21:23.000+01:00\"},\"maxValues\":{\"from_user\":\"user6\",\"to_user\":\"user50\",\"action\":\"SHARE\",\"event_time\":\"2025-12-13T17:21:26.000+01:00\"},\"nullCount\":{\"from_user\":0,\"to_user\":0,\"action\":0,\"event_time\":0}}"}}
