{"commitInfo":{"timestamp":1765651558361,"operation":"STREAMING UPDATE","operationParameters":{"outputMode":"Append","queryId":"6e90ed7b-5473-45ec-b504-d1723a761b48","epochId":"1292"},"readVersion":2041,"isolationLevel":"Serializable","isBlindAppend":true,"operationMetrics":{"numRemovedFiles":"0","numOutputRows":"25","numOutputBytes":"1599","numAddedFiles":"1"},"engineInfo":"Apache-Spark/3.5.7 Delta-Lake/3.1.0","txnId":"10579251-6554-4177-9952-7f1460e81411"}}
{"txn":{"appId":"6e90ed7b-5473-45ec-b504-d1723a761b48","version":1292,"lastUpdated":1765651558361}}
{"add":{"path":"part-00000-e70647dc-ff68-44e1-9563-31e728564985-c000.snappy.parquet","partitionValues":{},"size":1599,"modificationTime":1765651558354,"dataChange":true,"stats":"{\"numRecords\":25,\"minValues\":{\"from_user\":\"user1\",\"to_user\":\"user10\",\"action\":\"COMMENT\",\"event_time\":\"1970-01-21T11:27:31.551+01:00\"},\"maxValues\":{\"from_user\":\"user7\",\"to_user\":\"user6\",\"action\":\"SHARE\",\"event_time\":\"1970-01-21T11:27:31.556+01:00\"},\"nullCount\":{\"from_user\":0,\"to_user\":0,\"action\":0,\"event_time\":0}}"}}
