{"commitInfo":{"timestamp":1765648495469,"operation":"STREAMING UPDATE","operationParameters":{"outputMode":"Append","queryId":"6e90ed7b-5473-45ec-b504-d1723a761b48","epochId":"487"},"readVersion":1236,"isolationLevel":"Serializable","isBlindAppend":true,"operationMetrics":{"numRemovedFiles":"0","numOutputRows":"15","numOutputBytes":"1452","numAddedFiles":"1"},"engineInfo":"Apache-Spark/3.5.7 Delta-Lake/3.1.0","txnId":"041a277f-cf3f-4af7-b2bf-364520c7bff4"}}
{"txn":{"appId":"6e90ed7b-5473-45ec-b504-d1723a761b48","version":487,"lastUpdated":1765648495469}}
{"add":{"path":"part-00000-25b46a07-2ac6-467c-b531-36cf15728c16-c000.snappy.parquet","partitionValues":{},"size":1452,"modificationTime":1765648495460,"dataChange":true,"stats":"{\"numRecords\":15,\"minValues\":{\"from_user\":\"user1\",\"to_user\":\"user10\",\"action\":\"COMMENT\",\"event_time\":\"1970-01-21T11:27:28.491+01:00\"},\"maxValues\":{\"from_user\":\"user49\",\"to_user\":\"user6\",\"action\":\"SHARE\",\"event_time\":\"1970-01-21T11:27:28.494+01:00\"},\"nullCount\":{\"from_user\":0,\"to_user\":0,\"action\":0,\"event_time\":0}}"}}
