{"commitInfo":{"timestamp":1765643147876,"operation":"STREAMING UPDATE","operationParameters":{"outputMode":"Append","queryId":"c21f1fb7-6ebd-4aca-9520-4d1507940f2c","epochId":"741"},"readVersion":740,"isolationLevel":"Serializable","isBlindAppend":true,"operationMetrics":{"numRemovedFiles":"0","numOutputRows":"22","numOutputBytes":"1570","numAddedFiles":"1"},"engineInfo":"Apache-Spark/3.5.7 Delta-Lake/3.1.0","txnId":"b3f5d1b2-9f90-473f-9db7-ab8de3ef7956"}}
{"txn":{"appId":"c21f1fb7-6ebd-4aca-9520-4d1507940f2c","version":741,"lastUpdated":1765643147876}}
{"add":{"path":"part-00000-68693959-5744-4d8f-8ebe-56218f4748fe-c000.snappy.parquet","partitionValues":{},"size":1570,"modificationTime":1765643147871,"dataChange":true,"stats":"{\"numRecords\":22,\"minValues\":{\"from_user\":\"user10\",\"to_user\":\"user11\",\"action\":\"COMMENT\",\"event_time\":\"2025-12-13T17:25:42.000+01:00\"},\"maxValues\":{\"from_user\":\"user9\",\"to_user\":\"user6\",\"action\":\"SHARE\",\"event_time\":\"2025-12-13T17:25:46.000+01:00\"},\"nullCount\":{\"from_user\":0,\"to_user\":0,\"action\":0,\"event_time\":0}}"}}
