{"commitInfo":{"timestamp":1765641786716,"operation":"STREAMING UPDATE","operationParameters":{"outputMode":"Append","queryId":"c21f1fb7-6ebd-4aca-9520-4d1507940f2c","epochId":"261"},"readVersion":260,"isolationLevel":"Serializable","isBlindAppend":true,"operationMetrics":{"numRemovedFiles":"0","numOutputRows":"19","numOutputBytes":"1534","numAddedFiles":"1"},"engineInfo":"Apache-Spark/3.5.7 Delta-Lake/3.1.0","txnId":"50c3048f-f2db-4ae1-9a80-35f8d6f8da2b"}}
{"txn":{"appId":"c21f1fb7-6ebd-4aca-9520-4d1507940f2c","version":261,"lastUpdated":1765641786716}}
{"add":{"path":"part-00000-59baff09-8b36-45bf-976a-bb8b3fa46ded-c000.snappy.parquet","partitionValues":{},"size":1534,"modificationTime":1765641786710,"dataChange":true,"stats":"{\"numRecords\":19,\"minValues\":{\"from_user\":\"user11\",\"to_user\":\"user11\",\"action\":\"COMMENT\",\"event_time\":\"2025-12-13T17:03:01.000+01:00\"},\"maxValues\":{\"from_user\":\"user9\",\"to_user\":\"user7\",\"action\":\"SHARE\",\"event_time\":\"2025-12-13T17:03:05.000+01:00\"},\"nullCount\":{\"from_user\":0,\"to_user\":0,\"action\":0,\"event_time\":0}}"}}
